raja/CLAUDE.md
raja/__init__.py
raja/cedar/__init__.py
raja/cedar/entities.py
raja/cedar/parser.py
raja/cedar/schema.py
raja/compiler.py
raja/enforcer.py
raja/exceptions.py
raja/models.py
raja/py.typed
raja/rajee/__init__.py
raja/rajee/authorizer.py
raja/rajee/grants.py
raja/scope.py
raja/server/__init__.py
raja/server/app.py
raja/server/audit.py
raja/server/dependencies.py
raja/server/logging_config.py
raja/server/routers/__init__.py
raja/server/routers/control_plane.py
raja/server/routers/harness.py
raja/server/static/admin.css
raja/server/static/admin.js
raja/server/templates/admin.html
raja/token.py
raja-0.4.3.dist-info/WHEEL
raja-0.4.3.dist-info/METADATA
raja-0.4.3.dist-info/RECORD
