Metadata-Version: 2.3
Name: raja
Version: 0.4.3
Summary: Add your description here
Author: Dr. Ernie Prabhakar
Author-email: Dr. Ernie Prabhakar <ernest@quilt.bio>
Requires-Dist: pydantic>=2.7.0
Requires-Dist: pyjwt>=2.8.0
Requires-Dist: fastapi>=0.110.0
Requires-Dist: mangum>=0.17.0
Requires-Dist: structlog>=24.1.0
Requires-Dist: aws-cdk-lib>=2.100.0 ; extra == 'aws'
Requires-Dist: boto3>=1.34.0 ; extra == 'aws'
Requires-Dist: constructs>=10.0.0 ; extra == 'aws'
Requires-Dist: mypy>=1.7.0 ; extra == 'dev'
Requires-Dist: poethepoet>=0.24.0 ; extra == 'dev'
Requires-Dist: pytest>=8.0.0 ; extra == 'dev'
Requires-Dist: pytest-cov>=4.1.0 ; extra == 'dev'
Requires-Dist: pytest-watch>=4.2.0 ; extra == 'dev'
Requires-Dist: httpx>=0.27.0 ; extra == 'dev'
Requires-Dist: ruff>=0.1.0 ; extra == 'dev'
Requires-Dist: boto3-stubs[dynamodb,secretsmanager,verifiedpermissions]>=1.34.0 ; extra == 'dev'
Requires-Dist: moto>=4.2.0 ; extra == 'test'
Requires-Dist: pytest>=8.0.0 ; extra == 'test'
Requires-Dist: pytest-cov>=4.1.0 ; extra == 'test'
Requires-Dist: httpx>=0.27.0 ; extra == 'test'
Requires-Python: >=3.12
Provides-Extra: aws
Provides-Extra: dev
Provides-Extra: test
